[{"kind": "Listing", "data": {"modhash": "", "children": [{"kind": "t3", "data": {"domain": "self.SuicideWatch", "banned_by": null, "media_embed": {}, "subreddit": "SuicideWatch", "selftext_html": "&lt;!-- SC_OFF --&gt;&lt;div class=\"md\"&gt;&lt;p&gt;&lt;a href=\"http://www.reddit.com/r/SuicideWatch/comments/1ylxiu/i_am_tired/\"&gt;http://www.reddit.com/r/SuicideWatch/comments/1ylxiu/i_am_tired/&lt;/a&gt; link to last post. &lt;/p&gt;\n\n&lt;p&gt;I started listening to alot of music and watching more anime and I don&amp;#39;t feel depressed anymore. I still get said thinking of my cousin but I have distractions now with new video games coming out and play with my friends takes my mind of it. My dad is still struggling with work abit but stuffs getting better. I think I did better on my AP chem test then I expected.&lt;/p&gt;\n&lt;/div&gt;&lt;!-- SC_ON --&gt;", "selftext": "http://www.reddit.com/r/SuicideWatch/comments/1ylxiu/i_am_tired/ link to last post. \n\nI started listening to alot of music and watching more anime and I don't feel depressed anymore. I still get said thinking of my cousin but I have distractions now with new video games coming out and play with my friends takes my mind of it. My dad is still struggling with work abit but stuffs getting better. I think I did better on my AP chem test then I expected.", "likes": null, "secure_media": null, "link_flair_text": null, "id": "24x42b", "gilded": 0, "secure_media_embed": {}, "clicked": false, "stickied": false, "author": "W0LFSPIRIT", "media": null, "score": 2, "approved_by": null, "over_18": false, "hidden": false, "thumbnail": "", "subreddit_id": "t5_2qpzs", "edited": false, "link_flair_css_class": null, "author_flair_css_class": null, "downs": 0, "saved": false, "is_self": true, "permalink": "/r/SuicideWatch/comments/24x42b/im_feeling_a_bit_better/", "name": "t3_24x42b", "created": 1399458600.0, "url": "http://www.reddit.com/r/SuicideWatch/comments/24x42b/im_feeling_a_bit_better/", "author_flair_text": null, "title": "I'm feeling a bit better.", "created_utc": 1399429800.0, "ups": 2, "num_comments": 1, "visited": false, "num_reports": null, "distinguished": null}}], "after": null, "before": null}}, {"kind": "Listing", "data": {"modhash": "", "children": [{"kind": "t1", "data": {"subreddit_id": "t5_2qpzs", "banned_by": null, "subreddit": "SuicideWatch", "likes": null, "replies": "", "saved": false, "id": "chbrquq", "gilded": 0, "author": "womancat", "parent_id": "t3_24x42b", "approved_by": null, "body": "d(\u00b7__\u00b7)b life saving count: +1 Great job guys!", "edited": false, "author_flair_css_class": null, "downs": 0, "body_html": "&lt;div class=\"md\"&gt;&lt;p&gt;d(\u00b7__\u00b7)b life saving count: +1 Great job guys!&lt;/p&gt;\n&lt;/div&gt;", "link_id": "t3_24x42b", "score_hidden": false, "name": "t1_chbrquq", "created": 1399495613.0, "author_flair_text": null, "created_utc": 1399466813.0, "distinguished": null, "num_reports": null, "ups": 2}}], "after": null, "before": null}}]