[{"kind": "Listing", "data": {"modhash": "", "children": [{"kind": "t3", "data": {"domain": "self.SuicideWatch", "banned_by": null, "media_embed": {}, "subreddit": "SuicideWatch", "selftext_html": null, "selftext": "", "likes": null, "secure_media": null, "link_flair_text": null, "id": "24hi7c", "gilded": 0, "secure_media_embed": {}, "clicked": false, "stickied": false, "author": "dmjersak", "media": null, "score": 4, "approved_by": null, "over_18": false, "hidden": false, "thumbnail": "", "subreddit_id": "t5_2qpzs", "edited": false, "link_flair_css_class": null, "author_flair_css_class": null, "downs": 0, "saved": false, "is_self": true, "permalink": "/r/SuicideWatch/comments/24hi7c/see_ya/", "name": "t3_24hi7c", "created": 1399005766.0, "url": "http://www.reddit.com/r/SuicideWatch/comments/24hi7c/see_ya/", "author_flair_text": null, "title": "See ya", "created_utc": 1398976966.0, "ups": 4, "num_comments": 4, "visited": false, "num_reports": null, "distinguished": null}}], "after": null, "before": null}}, {"kind": "Listing", "data": {"modhash": "", "children": [{"kind": "t1", "data": {"subreddit_id": "t5_2qpzs", "banned_by": null, "subreddit": "SuicideWatch", "likes": null, "replies": "", "saved": false, "id": "ch760gf", "gilded": 0, "author": "[deleted]", "parent_id": "t3_24hi7c", "approved_by": null, "body": "Hey, I don't know exactly what you're going through here but you wouldn't be posting if you didn't want to talk to someone. Just spend a couple of minutes if you can telling me what exactly you are going through now, please.", "edited": false, "author_flair_css_class": null, "downs": 0, "body_html": "&lt;div class=\"md\"&gt;&lt;p&gt;Hey, I don&amp;#39;t know exactly what you&amp;#39;re going through here but you wouldn&amp;#39;t be posting if you didn&amp;#39;t want to talk to someone. Just spend a couple of minutes if you can telling me what exactly you are going through now, please.&lt;/p&gt;\n&lt;/div&gt;", "link_id": "t3_24hi7c", "score_hidden": false, "name": "t1_ch760gf", "created": 1399005967.0, "author_flair_text": null, "created_utc": 1398977167.0, "distinguished": null, "num_reports": null, "ups": 3}}, {"kind": "t1", "data": {"subreddit_id": "t5_2qpzs", "banned_by": null, "subreddit": "SuicideWatch", "likes": null, "replies": "", "saved": false, "id": "ch77lmp", "gilded": 0, "author": "raffnix", "parent_id": "t3_24hi7c", "approved_by": null, "body": "Whats going on?", "edited": false, "author_flair_css_class": null, "downs": 0, "body_html": "&lt;div class=\"md\"&gt;&lt;p&gt;Whats going on?&lt;/p&gt;\n&lt;/div&gt;", "link_id": "t3_24hi7c", "score_hidden": false, "name": "t1_ch77lmp", "created": 1399009311.0, "author_flair_text": null, "created_utc": 1398980511.0, "distinguished": null, "num_reports": null, "ups": 2}}, {"kind": "t1", "data": {"subreddit_id": "t5_2qpzs", "banned_by": null, "subreddit": "SuicideWatch", "likes": null, "replies": "", "saved": false, "id": "ch77mll", "gilded": 0, "author": "ventimhere", "parent_id": "t3_24hi7c", "approved_by": null, "body": "Hey how are you doing? Could you let us know what is happening please? ", "edited": false, "author_flair_css_class": null, "downs": 0, "body_html": "&lt;div class=\"md\"&gt;&lt;p&gt;Hey how are you doing? Could you let us know what is happening please? &lt;/p&gt;\n&lt;/div&gt;", "link_id": "t3_24hi7c", "score_hidden": false, "name": "t1_ch77mll", "created": 1398984169.0, "author_flair_text": null, "created_utc": 1398980569.0, "distinguished": null, "num_reports": null, "ups": 2}}, {"kind": "t1", "data": {"subreddit_id": "t5_2qpzs", "banned_by": null, "subreddit": "SuicideWatch", "likes": null, "replies": "", "saved": false, "id": "ch79c1i", "gilded": 0, "author": "Soletrador", "parent_id": "t3_24hi7c", "approved_by": null, "body": "You still here?\n\nAnswer me please!", "edited": false, "author_flair_css_class": null, "downs": 0, "body_html": "&lt;div class=\"md\"&gt;&lt;p&gt;You still here?&lt;/p&gt;\n\n&lt;p&gt;Answer me please!&lt;/p&gt;\n&lt;/div&gt;", "link_id": "t3_24hi7c", "score_hidden": false, "name": "t1_ch79c1i", "created": 1398987980.0, "author_flair_text": null, "created_utc": 1398984380.0, "distinguished": null, "num_reports": null, "ups": 2}}], "after": null, "before": null}}]