[{"kind": "Listing", "data": {"modhash": "", "children": [{"kind": "t3", "data": {"domain": "i.imgur.com", "banned_by": null, "media_embed": {}, "subreddit": "happy", "selftext_html": null, "selftext": "", "likes": null, "secure_media": null, "link_flair_text": null, "id": "24uj9q", "gilded": 0, "secure_media_embed": {}, "clicked": false, "stickied": false, "author": "mmBread", "media": null, "score": 5, "approved_by": null, "over_18": false, "hidden": false, "thumbnail": "http://c.thumbs.redditmedia.com/CozfMDOOUyaGt66b.jpg", "subreddit_id": "t5_2qh5i", "edited": false, "link_flair_css_class": null, "author_flair_css_class": null, "downs": 2, "saved": false, "is_self": false, "permalink": "/r/happy/comments/24uj9q/i_bought_my_first_stethoscope_and_sphygmomanometer/", "name": "t3_24uj9q", "created": 1399391298.0, "url": "http://i.imgur.com/Zcckqdu.jpg", "author_flair_text": null, "title": "I bought my first stethoscope and sphygmomanometer!", "created_utc": 1399362498.0, "ups": 7, "num_comments": 1, "visited": false, "num_reports": null, "distinguished": null}}], "after": null, "before": null}}, {"kind": "Listing", "data": {"modhash": "", "children": [{"kind": "t1", "data": {"subreddit_id": "t5_2qh5i", "banned_by": null, "subreddit": "happy", "likes": null, "replies": "", "saved": false, "id": "chat37k", "gilded": 0, "author": "ipanderi", "parent_id": "t3_24uj9q", "approved_by": null, "body": "Litman ii's those are solid ", "edited": false, "author_flair_css_class": null, "downs": 0, "body_html": "&lt;div class=\"md\"&gt;&lt;p&gt;Litman ii&amp;#39;s those are solid &lt;/p&gt;\n&lt;/div&gt;", "link_id": "t3_24uj9q", "score_hidden": false, "name": "t1_chat37k", "created": 1399393049.0, "author_flair_text": null, "created_utc": 1399364249.0, "distinguished": null, "num_reports": null, "ups": 1}}], "after": null, "before": null}}]