[{"kind": "Listing", "data": {"modhash": "", "children": [{"kind": "t3", "data": {"domain": "imgur.com", "banned_by": null, "media_embed": {}, "subreddit": "happy", "selftext_html": null, "selftext": "", "likes": null, "secure_media": null, "link_flair_text": null, "id": "22djqe", "gilded": 0, "secure_media_embed": {}, "clicked": false, "stickied": false, "author": "penny-pox", "media": null, "score": 8, "approved_by": null, "over_18": false, "hidden": false, "thumbnail": "http://a.thumbs.redditmedia.com/zCRaLAbXnsdrfFqr.jpg", "subreddit_id": "t5_2qh5i", "edited": false, "link_flair_css_class": null, "author_flair_css_class": null, "downs": 4, "saved": false, "is_self": false, "permalink": "/r/happy/comments/22djqe/i_love_living_with_med_students/", "name": "t3_22djqe", "created": 1396850869.0, "url": "http://imgur.com/ikYEOdW", "author_flair_text": null, "title": "I love living with med students :)", "created_utc": 1396822069.0, "ups": 12, "num_comments": 1, "visited": false, "num_reports": null, "distinguished": null}}], "after": null, "before": null}}, {"kind": "Listing", "data": {"modhash": "", "children": [{"kind": "t1", "data": {"subreddit_id": "t5_2qh5i", "banned_by": null, "subreddit": "happy", "likes": null, "replies": "", "saved": false, "id": "cglw488", "gilded": 0, "author": "TheKnittyWit", "parent_id": "t3_22djqe", "approved_by": null, "body": "It looks like they have the makings of a great doctor! ", "edited": false, "author_flair_css_class": null, "downs": 0, "body_html": "&lt;div class=\"md\"&gt;&lt;p&gt;It looks like they have the makings of a great doctor! &lt;/p&gt;\n&lt;/div&gt;", "link_id": "t3_22djqe", "score_hidden": false, "name": "t1_cglw488", "created": 1396838420.0, "author_flair_text": null, "created_utc": 1396834820.0, "distinguished": null, "num_reports": null, "ups": 2}}], "after": null, "before": null}}]