[{"kind": "Listing", "data": {"modhash": "", "children": [{"kind": "t3", "data": {"domain": "i.imgur.com", "banned_by": null, "media_embed": {}, "subreddit": "happy", "selftext_html": null, "selftext": "", "likes": null, "secure_media": null, "link_flair_text": null, "id": "2441hi", "gilded": 0, "secure_media_embed": {}, "clicked": false, "stickied": false, "author": "CarpenterDan", "media": null, "score": 13, "approved_by": null, "over_18": false, "hidden": false, "thumbnail": "http://b.thumbs.redditmedia.com/9ryfyCU9eDFri611.jpg", "subreddit_id": "t5_2qh5i", "edited": false, "link_flair_css_class": null, "author_flair_css_class": null, "downs": 3, "saved": false, "is_self": false, "permalink": "/r/happy/comments/2441hi/wont_you_come_and_join_me_on_my_float/", "name": "t3_2441hi", "created": 1398644489.0, "url": "http://i.imgur.com/CNQPUmp.jpg", "author_flair_text": null, "title": "Won't you come and join me on my float?", "created_utc": 1398615689.0, "ups": 16, "num_comments": 0, "visited": false, "num_reports": null, "distinguished": null}}], "after": null, "before": null}}, {"kind": "Listing", "data": {"modhash": "", "children": [], "after": null, "before": null}}]